fc2/__init__.py
fc2/auth.py
fc2/client.py
fc2/fc_exceptions.py
fc2/util.py
xl_aliyun_fc2-0.0.2.dist-info/LICENSE
xl_aliyun_fc2-0.0.2.dist-info/METADATA
xl_aliyun_fc2-0.0.2.dist-info/WHEEL
xl_aliyun_fc2-0.0.2.dist-info/top_level.txt
xl_aliyun_fc2-0.0.2.dist-info/RECORD
