Metadata-Version: 2.1
Name: xl-aliyun-fc2
Version: 0.0.2
Summary: xiliu Aliyun FunctionCompute SDK2
Home-page: https://www.aliyun.com/product/fc
Classifier: Development Status :: 5 - Production/Stable
Classifier: Intended Audience :: Developers
Classifier: License :: OSI Approved :: MIT License
Classifier: Operating System :: OS Independent
Classifier: Programming Language :: Python
Classifier: Programming Language :: Python :: 3.6
Classifier: Programming Language :: Python :: 3.7
Classifier: Programming Language :: Python :: 3.8
Classifier: Programming Language :: Python :: 3.9
Classifier: Programming Language :: Python :: 3.10
License-File: LICENSE
Requires-Dist: requests (>=2.20.0)
Requires-Dist: websocket-client (>=1.4.1)
